viggoparceiro/__init__.py
viggoparceiro/resources.py
viggoparceiro/subsystem/__init__.py
viggoparceiro/subsystem/parceiro/__init__.py
viggoparceiro/subsystem/parceiro/manager.py
viggoparceiro/subsystem/parceiro/resource.py
viggoparceiro/tests/__init__.py
viggoparceiro/tests/functional/__init__.py
viggoparceiro/tests/functional/fixtures.py
viggoparceiro-1.1.1.dist-info/AUTHORS
viggoparceiro-1.1.1.dist-info/METADATA
viggoparceiro-1.1.1.dist-info/WHEEL
viggoparceiro-1.1.1.dist-info/top_level.txt
viggoparceiro-1.1.1.dist-info/RECORD
