Metadata-Version: 2.1
Name: viggoparceiro
Version: 1.1.1
Summary: ViggoParceiro Backend Flask REST service
Home-page: UNKNOWN
License: UNKNOWN
Platform: UNKNOWN
License-File: AUTHORS
Requires-Dist: viggocore<2.0.0,>=1.0.0
Requires-Dist: viggolocal>=1.0.0
Requires-Dist: flask-cors
